corgi/__init__.py
corgi/apps.py
corgi/archive/data-old.py
corgi/archive/profiling.py
corgi/archive/tensor.py
corgi/archive/transforms.py
corgi/data.py
corgi/models.py
corgi/refseq.py
corgi/seqtree.py
bio_corgi-0.5.1.dist-info/LICENSE
bio_corgi-0.5.1.dist-info/METADATA
bio_corgi-0.5.1.dist-info/WHEEL
bio_corgi-0.5.1.dist-info/entry_points.txt
bio_corgi-0.5.1.dist-info/RECORD
