Metadata-Version: 2.3
Name: bio-corgi
Version: 0.5.1
Summary: Classifier for ORganelle Genomes Inter alia
License: Apache Software License 2.0
Keywords: metagenomic classifier,tiara,DNA,bioinformatics,lightning,pytorch,deep learning,command-line interface
Author: Robert Turnbull
Author-email: robert.turnbull@unimelb.edu.au
Requires-Python: >=3.10,<3.13
Classifier: Intended Audience :: Science/Research
Classifier: License :: OSI Approved :: Apache Software License
Classifier: License :: Other/Proprietary License
Classifier: Programming Language :: Python :: 3
Classifier: Programming Language :: Python :: 3.10
Classifier: Programming Language :: Python :: 3.11
Classifier: Programming Language :: Python :: 3.12
Classifier: Topic :: Scientific/Engineering :: Artificial Intelligence
Classifier: Topic :: Scientific/Engineering :: Bio-Informatics
Classifier: Topic :: Software Development :: Libraries :: Python Modules
Requires-Dist: PyMySQL (>=1.0.2)
Requires-Dist: appdirs (>=1.4.4)
Requires-Dist: attrs (>=23.1.0)
Requires-Dist: beautifulsoup4 (>=4.10.0)
Requires-Dist: biopython (>=1.79)
Requires-Dist: cryptography (>=36.0.1)
Requires-Dist: hierarchicalsoftmax (>=1.4.1)
Requires-Dist: httpx (>=0.20.0)
Requires-Dist: humanize (>=3.10.0)
Requires-Dist: multitax (>=1.3.1)
Requires-Dist: numpy (<2.0.0)
Requires-Dist: plotly (>=5.3.1)
Requires-Dist: polytorch (>=0.1.3)
Requires-Dist: pyarrow (>=5.0.0)
Requires-Dist: seqbank (>=0.1.3)
Requires-Dist: termgraph (>=0.5.3)
Requires-Dist: torch (>=2.0.0)
Requires-Dist: torchapp (>=0.5.2)
Project-URL: Documentation, https://rbturnbull.github.io/corgi/
Project-URL: Homepage, https://github.com/rbturnbull/corgi
Project-URL: Repository, https://github.com/rbturnbull/corgi
